{"version": "5.4.1", "flags": {}, "shapes": [{"label": "commercial_building", "points": [[384.0, 384.0], [322.2598870056497, 279.03389830508473]], "group_id": "null", "description": "", "shape_type": "rectangle", "flags": {}, "mask": "null"}, {"label": "residential_building", "points": [[149.94350282485874, 336.6610169491525], [128.0, 279.59887005649716]], "group_id": "null", "description": "", "shape_type": "rectangle", "flags": {}, "mask": "null"}, {"label": "residential_building", "points": [[191.75141242937855, 341.74576271186436], [155.0282485875706, 286.3785310734463]], "group_id": "null", "description": "", "shape_type": "rectangle", "flags": {}, "mask": "null"}, {"label": "residential_building", "points": [[240.33898305084745, 348.5254237288135], [192.31638418079098, 262.6497175141243]], "group_id": "null", "description": "", "shape_type": "rectangle", "flags": {}, "mask": "null"}, {"label": "residential_building", "points": [[285.5367231638418, 352.4802259887005], [243.1638418079096, 297.6779661016949]], "group_id": "null", "description": "", "shape_type": "rectangle", "flags": {}, "mask": "null"}]}